mintlabs/Account.py
mintlabs/Project.py
mintlabs/Subject.py
mintlabs/__init__.py
mintlabs-0.2.588.dist-info/DESCRIPTION.rst
mintlabs-0.2.588.dist-info/METADATA
mintlabs-0.2.588.dist-info/RECORD
mintlabs-0.2.588.dist-info/WHEEL
mintlabs-0.2.588.dist-info/metadata.json
mintlabs-0.2.588.dist-info/namespace_packages.txt
mintlabs-0.2.588.dist-info/top_level.txt
