Metadata-Version: 2.0
Name: mintlabs
Version: 0.2.588
Summary: This is the Python API to interact with the Mint-Labs platform.
Home-page: http://www.mint-labs.com/
Author: Mint Labs
Author-email: support@mint-labs.com
License: MIT
Platform: UNKNOWN
Requires-Dist: nose
Requires-Dist: nose-xunitmp
Requires-Dist: requests
